fetch_lyrics_from_genius/__init__.py
fetch_lyrics_from_genius/fetch_lyrics.py
fetch_lyrics_from_genius-0.1.2.dist-info/LICENSE
fetch_lyrics_from_genius-0.1.2.dist-info/METADATA
fetch_lyrics_from_genius-0.1.2.dist-info/WHEEL
fetch_lyrics_from_genius-0.1.2.dist-info/entry_points.txt
fetch_lyrics_from_genius-0.1.2.dist-info/top_level.txt
fetch_lyrics_from_genius-0.1.2.dist-info/RECORD
